{
  "id": "20369434-9cc5-423c-9f97-2e79e2fd3882",
  "title": "Afternoon workout \ud83d\udcaa",
  "routine_id": null,
  "description": "",
  "start_time": "2025-01-02T06:13:19+00:00",
  "end_time": "2025-01-02T07:02:39+00:00",
  "updated_at": "2025-01-02T07:02:40.630Z",
  "created_at": "2025-01-02T07:02:40.630Z",
  "exercises": [
    {
      "index": 0,
      "title": "Bench Press (Dumbbell)",
      "notes": "",
      "exercise_template_id": "3601968B",
      "superset_id": null,
      "sets": [
        {
          "index": 0,
          "type": "normal",
          "weight_kg": 20,
          "reps": 5,
          "distance_meters": null,
          "duration_seconds": null,
          "rpe": null,
          "custom_metric": null
        },
        {
          "index": 1,
          "type": "normal",
          "weight_kg": 75,
          "reps": 5,
          "distance_meters": null,
          "duration_seconds": null,
          "rpe": null,
          "custom_metric": null
        },
        {
          "index": 2,
          "type": "normal",
          "weight_kg": 85,
          "reps": 4,
          "distance_meters": null,
          "duration_seconds": null,
          "rpe": null,
          "custom_metric": null
        },
        {
          "index": 3,
          "type": "failure",
          "weight_kg": 75,
          "reps": 4,
          "distance_meters": null,
          "duration_seconds": null,
          "rpe": null,
          "custom_metric": null
        }
      ]
    },
    {
      "index": 1,
      "title": "Shoulder Press (Dumbbell)",
      "notes": "",
      "exercise_template_id": "878CD1D0",
      "superset_id": null,
      "sets": [
        {
          "index": 0,
          "type": "normal",
          "weight_kg": 50,
          "reps": 8,
          "distance_meters": null,
          "duration_seconds": null,
          "rpe": null,
          "custom_metric": null
        },
        {
          "index": 1,
          "type": "failure",
          "weight_kg": 50,
          "reps": 7,
          "distance_meters": null,
          "duration_seconds": null,
          "rpe": null,
          "custom_metric": null
        },
        {
          "index": 2,
          "type": "normal",
          "weight_kg": 50,
          "reps": 7,
          "distance_meters": null,
          "duration_seconds": null,
          "rpe": null,
          "custom_metric": null
        }
      ]
    },
    {
      "index": 2,
      "title": "Chest Fly (Machine)",
      "notes": "",
      "exercise_template_id": "78683336",
      "superset_id": null,
      "sets": [
        {
          "index": 0,
          "type": "normal",
          "weight_kg": 57,
          "reps": 12,
          "distance_meters": null,
          "duration_seconds": null,
          "rpe": null,
          "custom_metric": null
        },
        {
          "index": 1,
          "type": "normal",
          "weight_kg": 57,
          "reps": 12,
          "distance_meters": null,
          "duration_seconds": null,
          "rpe": null,
          "custom_metric": null
        },
        {
          "index": 2,
          "type": "normal",
          "weight_kg": 57,
          "reps": 12,
          "distance_meters": null,
          "duration_seconds": null,
          "rpe": null,
          "custom_metric": null
        }
      ]
    },
    {
      "index": 3,
      "title": "Lateral Raise (Dumbbell)",
      "notes": "",
      "exercise_template_id": "422B08F1",
      "superset_id": null,
      "sets": [
        {
          "index": 0,
          "type": "normal",
          "weight_kg": 10,
          "reps": 12,
          "distance_meters": null,
          "duration_seconds": null,
          "rpe": null,
          "custom_metric": null
        },
        {
          "index": 1,
          "type": "normal",
          "weight_kg": 10,
          "reps": 12,
          "distance_meters": null,
          "duration_seconds": null,
          "rpe": null,
          "custom_metric": null
        },
        {
          "index": 2,
          "type": "failure",
          "weight_kg": 10,
          "reps": 10,
          "distance_meters": null,
          "duration_seconds": null,
          "rpe": null,
          "custom_metric": null
        }
      ]
    },
    {
      "index": 4,
      "title": "Seated Dip Machine",
      "notes": "",
      "exercise_template_id": "5122E7D9",
      "superset_id": null,
      "sets": [
        {
          "index": 0,
          "type": "normal",
          "weight_kg": 57,
          "reps": 15,
          "distance_meters": null,
          "duration_seconds": null,
          "rpe": null,
          "custom_metric": null
        },
        {
          "index": 1,
          "type": "normal",
          "weight_kg": 70,
          "reps": 12,
          "distance_meters": null,
          "duration_seconds": null,
          "rpe": null,
          "custom_metric": null
        },
        {
          "index": 2,
          "type": "failure",
          "weight_kg": 84,
          "reps": 10,
          "distance_meters": null,
          "duration_seconds": null,
          "rpe": null,
          "custom_metric": null
        },
        {
          "index": 3,
          "type": "failure",
          "weight_kg": 91,
          "reps": 10,
          "distance_meters": null,
          "duration_seconds": null,
          "rpe": null,
          "custom_metric": null
        }
      ]
    },
    {
      "index": 5,
      "title": "Triceps Kickback (Cable)",
      "notes": "",
      "exercise_template_id": "EC3B69A3",
      "superset_id": null,
      "sets": [
        {
          "index": 0,
          "type": "normal",
          "weight_kg": 13.6,
          "reps": 12,
          "distance_meters": null,
          "duration_seconds": null,
          "rpe": null,
          "custom_metric": null
        },
        {
          "index": 1,
          "type": "normal",
          "weight_kg": 13.6,
          "reps": 9,
          "distance_meters": null,
          "duration_seconds": null,
          "rpe": null,
          "custom_metric": null
        }
      ]
    }
  ]
}