{
  "id": "5539910b-e29d-4dc0-9a69-2039ca7715bd",
  "title": "2026: Pull",
  "routine_id": "8e7268e0-7617-4798-bf50-3dd421196dbd",
  "description": "",
  "start_time": "2026-04-14T14:06:14+00:00",
  "end_time": "2026-04-14T15:03:20+00:00",
  "updated_at": "2026-04-14T15:03:16.222Z",
  "created_at": "2026-04-14T15:03:16.222Z",
  "exercises": [
    {
      "index": 0,
      "title": "Cable Core Palloff Press",
      "notes": "Push shoulders all the way. Cable height 8.\n\nTried 15.9kg but too heavy and started slipping on seat.\n\nHolding at extended length for about 3 seconds.\n\nThe cable machine pivot angle moves slightly with my movement. Is this okay?",
      "exercise_template_id": "CC55119B",
      "superset_id": null,
      "sets": [
        {
          "index": 0,
          "type": "warmup",
          "weight_kg": 2.3,
          "reps": 7,
          "distance_meters": null,
          "duration_seconds": null,
          "rpe": 6,
          "custom_metric": null
        },
        {
          "index": 1,
          "type": "normal",
          "weight_kg": 9.1,
          "reps": 4,
          "distance_meters": null,
          "duration_seconds": null,
          "rpe": 10,
          "custom_metric": null
        },
        {
          "index": 2,
          "type": "normal",
          "weight_kg": 6.8,
          "reps": 6,
          "distance_meters": null,
          "duration_seconds": null,
          "rpe": 10,
          "custom_metric": null
        },
        {
          "index": 3,
          "type": "normal",
          "weight_kg": 6.8,
          "reps": 5,
          "distance_meters": null,
          "duration_seconds": null,
          "rpe": 10,
          "custom_metric": null
        }
      ]
    },
    {
      "index": 1,
      "title": "Back Extension (Weighted Hyperextension)",
      "notes": "",
      "exercise_template_id": "091737FA",
      "superset_id": null,
      "sets": [
        {
          "index": 0,
          "type": "normal",
          "weight_kg": 0,
          "reps": 5,
          "distance_meters": null,
          "duration_seconds": null,
          "rpe": 10,
          "custom_metric": null
        },
        {
          "index": 1,
          "type": "normal",
          "weight_kg": 0,
          "reps": 5,
          "distance_meters": null,
          "duration_seconds": null,
          "rpe": 10,
          "custom_metric": null
        },
        {
          "index": 2,
          "type": "normal",
          "weight_kg": 0,
          "reps": 4,
          "distance_meters": null,
          "duration_seconds": null,
          "rpe": 10,
          "custom_metric": null
        }
      ]
    },
    {
      "index": 2,
      "title": "Face Pull",
      "notes": "Set 1 bench on setting 6 cable on setting 12\nSet 2 bench on setting 7 cable on setting 12\nSet 3 moved cable setting 11 to try move hands above elbows better",
      "exercise_template_id": "BE640BA0",
      "superset_id": null,
      "sets": [
        {
          "index": 0,
          "type": "normal",
          "weight_kg": 9.1,
          "reps": 8,
          "distance_meters": null,
          "duration_seconds": null,
          "rpe": 10,
          "custom_metric": null
        },
        {
          "index": 1,
          "type": "normal",
          "weight_kg": 9.1,
          "reps": 8,
          "distance_meters": null,
          "duration_seconds": null,
          "rpe": 10,
          "custom_metric": null
        },
        {
          "index": 2,
          "type": "normal",
          "weight_kg": 9.1,
          "reps": 4,
          "distance_meters": null,
          "duration_seconds": null,
          "rpe": 10,
          "custom_metric": null
        }
      ]
    },
    {
      "index": 3,
      "title": "Iso-Lateral Row (Machine)",
      "notes": "Neutral/vertical grip. Assuming base weight is 0kg.\n\nSet 1 + 2: bicep bottleneck",
      "exercise_template_id": "AA1EB7D8",
      "superset_id": null,
      "sets": [
        {
          "index": 0,
          "type": "normal",
          "weight_kg": 40,
          "reps": 8,
          "distance_meters": null,
          "duration_seconds": null,
          "rpe": 10,
          "custom_metric": null
        },
        {
          "index": 1,
          "type": "normal",
          "weight_kg": 40,
          "reps": 7,
          "distance_meters": null,
          "duration_seconds": null,
          "rpe": 10,
          "custom_metric": null
        },
        {
          "index": 2,
          "type": "normal",
          "weight_kg": 40,
          "reps": 6,
          "distance_meters": null,
          "duration_seconds": null,
          "rpe": 10,
          "custom_metric": null
        }
      ]
    },
    {
      "index": 4,
      "title": "Lat Pulldown (Cable)",
      "notes": "Set 1: Slower\nSet 2: Faster but still controlled\nSet 3: Faster but still controlled",
      "exercise_template_id": "6A6C31A5",
      "superset_id": null,
      "sets": [
        {
          "index": 0,
          "type": "normal",
          "weight_kg": 52,
          "reps": 6,
          "distance_meters": null,
          "duration_seconds": null,
          "rpe": 10,
          "custom_metric": null
        },
        {
          "index": 1,
          "type": "normal",
          "weight_kg": 52,
          "reps": 6,
          "distance_meters": null,
          "duration_seconds": null,
          "rpe": 10,
          "custom_metric": null
        },
        {
          "index": 2,
          "type": "normal",
          "weight_kg": 52,
          "reps": 5,
          "distance_meters": null,
          "duration_seconds": null,
          "rpe": 10,
          "custom_metric": null
        }
      ]
    },
    {
      "index": 5,
      "title": "Rear Delt Reverse Fly (Machine)",
      "notes": "Neutral grip palms facing each other.",
      "exercise_template_id": "D8281C62",
      "superset_id": null,
      "sets": [
        {
          "index": 0,
          "type": "normal",
          "weight_kg": 32,
          "reps": 10,
          "distance_meters": null,
          "duration_seconds": null,
          "rpe": 10,
          "custom_metric": null
        },
        {
          "index": 1,
          "type": "normal",
          "weight_kg": 32,
          "reps": 7,
          "distance_meters": null,
          "duration_seconds": null,
          "rpe": 10,
          "custom_metric": null
        }
      ]
    },
    {
      "index": 6,
      "title": "Preacher Curl (Barbell)",
      "notes": "",
      "exercise_template_id": "4F942934",
      "superset_id": null,
      "sets": [
        {
          "index": 0,
          "type": "normal",
          "weight_kg": 12.5,
          "reps": 15,
          "distance_meters": null,
          "duration_seconds": null,
          "rpe": 10,
          "custom_metric": null
        },
        {
          "index": 1,
          "type": "normal",
          "weight_kg": 15,
          "reps": 6,
          "distance_meters": null,
          "duration_seconds": null,
          "rpe": 10,
          "custom_metric": null
        }
      ]
    }
  ]
}